aegislog/__init__.py
aegislog/auto_logger.py
aegislog/client.py
aegislog/exceptions.py
aegislog-3.0.0.dist-info/METADATA
aegislog-3.0.0.dist-info/WHEEL
aegislog-3.0.0.dist-info/top_level.txt
aegislog-3.0.0.dist-info/RECORD
