Metadata-Version: 2.4
Name: aegislog
Version: 3.0.0
Summary: Fire-and-Forget Evidence Logging for EU AI Act Compliance with Time Machine Defense
Author-email: Prolixo Defense <engineering@prolixo.dev>
License: MIT
Project-URL: Homepage, https://github.com/prolixo-defense/aegislog
Project-URL: Documentation, https://docs.prolixo.dev/aegislog
Project-URL: Repository, https://github.com/prolixo-defense/aegislog
Keywords: ai,compliance,eu-ai-act,logging,evidence,audit,article-12,article-14,traceability
Classifier: Development Status :: 5 - Production/Stable
Classifier: Intended Audience :: Developers
Classifier: License :: OSI Approved :: MIT License
Classifier: Programming Language :: Python :: 3
Classifier: Programming Language :: Python :: 3.8
Classifier: Programming Language :: Python :: 3.9
Classifier: Programming Language :: Python :: 3.10
Classifier: Programming Language :: Python :: 3.11
Classifier: Programming Language :: Python :: 3.12
Classifier: Topic :: Software Development :: Libraries :: Python Modules
Classifier: Topic :: System :: Logging
Requires-Python: >=3.8
Provides-Extra: async
Requires-Dist: aiohttp>=3.8.0; extra == "async"
Provides-Extra: dev
Requires-Dist: pytest; extra == "dev"
Requires-Dist: pytest-asyncio; extra == "dev"
Requires-Dist: aiohttp; extra == "dev"
